se3/__init__.py
se3/ai/__init__.py
se3.ai-0.0.2.dist-info/METADATA
se3.ai-0.0.2.dist-info/WHEEL
se3.ai-0.0.2.dist-info/top_level.txt
se3.ai-0.0.2.dist-info/RECORD
